open_gpt/__init__.py
open_gpt/__main__.py
open_gpt/factory.py
open_gpt/helper.py
open_gpt/logs.py
open_gpt/profile.py
open_gpt/cli/__init__.py
open_gpt/cli/application.py
open_gpt/cli/command_loader.py
open_gpt/cli/commands/__init__.py
open_gpt/cli/commands/about.py
open_gpt/cli/commands/deploy.py
open_gpt/cli/commands/playground.py
open_gpt/cli/commands/quantize.py
open_gpt/cli/commands/serve.py
open_gpt/models/__init__.py
open_gpt/models/embedding.py
open_gpt/models/generation.py
open_gpt/models/loading.py
open_gpt/models/modeling.py
open_gpt/models/session.py
open_gpt/models/flamingo/__init__.py
open_gpt/models/flamingo/configuration_flamingo.py
open_gpt/models/flamingo/flamingo_lm.py
open_gpt/models/flamingo/flamingo_model.py
open_gpt/models/flamingo/loading.py
open_gpt/models/flamingo/modeling.py
open_gpt/models/llama/__init__.py
open_gpt/models/llama/loading.py
open_gpt/models/llama/modeling.py
open_gpt/models/moss/__init__.py
open_gpt/models/moss/modeling.py
open_gpt/models/pythia/__init__.py
open_gpt/models/pythia/modeling.py
open_gpt/models/rwkv/__init__.py
open_gpt/models/rwkv/modeling.py
open_gpt/models/stablelm/__init__.py
open_gpt/models/stablelm/modeling.py
open_gpt/models/vicuna/__init__.py
open_gpt/models/vicuna/loading.py
open_gpt/models/vicuna/modeling.py
open_gpt/serve/__init__.py
open_gpt/serve/flow.py
open_gpt/serve/gateway.py
open_gpt/serve/executors/__init__.py
open_gpt/serve/executors/base.py
open_gpt/serve/executors/flamingo.py
open_gpt/serve/executors/utils.py
open_gpt/serve/playground/__init__.py
open_gpt/serve/playground/gradio.py
open_gpt/serve/playground/gradio_chatbot.py
open_gpt/serve/playground/gradio_css.py
open_gpt_torch-0.0.13.dist-info/LICENSE
open_gpt_torch-0.0.13.dist-info/METADATA
open_gpt_torch-0.0.13.dist-info/WHEEL
open_gpt_torch-0.0.13.dist-info/entry_points.txt
open_gpt_torch-0.0.13.dist-info/top_level.txt
open_gpt_torch-0.0.13.dist-info/RECORD
